google_api_helper-0.3.0.dist-info/DESCRIPTION.rst
google_api_helper-0.3.0.dist-info/METADATA
google_api_helper-0.3.0.dist-info/RECORD
google_api_helper-0.3.0.dist-info/WHEEL
google_api_helper-0.3.0.dist-info/metadata.json
google_api_helper-0.3.0.dist-info/top_level.txt
googleapi/__init__.py
googleapi/api.py
googleapi/oauth2.py
