Metadata-Version: 2.0
Name: google-api-helper
Version: 0.3.0
Summary: Python helper class to streamlime interaction with Google APIs. Based on python-google-api-client.
Home-page: https://github.com/r00tat/google-api-helper
Author: Paul Woelfel
Author-email: github@frig.at
License: GNU GPL v3
Keywords: google api python
Platform: UNKNOWN
Classifier: Development Status :: 3 - Alpha
Classifier: Intended Audience :: Developers
Classifier: Topic :: Software Development :: Libraries
Classifier: License :: OSI Approved :: GNU General Public License v3 (GPLv3)
Classifier: Programming Language :: Python :: 2
Classifier: Programming Language :: Python :: 2.7
Classifier: Programming Language :: Python :: 3
Classifier: Programming Language :: Python :: 3.3
Classifier: Programming Language :: Python :: 3.4
Classifier: Programming Language :: Python :: 3.5
Requires-Dist: google-api-python-client
Requires-Dist: google-auth
Requires-Dist: google-auth-oauthlib
Provides-Extra: dev
Provides-Extra: test
